{"&cites=16226282136791287795&as_sdt=2005&sciodt=0,5&hl=en":[{"title":"The data revolution: Big data, open data, data infrastructures and their consequences","url":"https://books.google.com/books?hl=en&lr=&id=GfOICwAAQBAJ&oi=fnd&pg=PP1&ots=pdzhO_Yn-X&sig=1VtPslkj8X9ZQUfn6xU4Ybfaw0I","authors":["R Kitchin"],"year":2014,"numCitations":1717,"pdf":"http://dln.jaipuria.ac.in:8080/jspui/bitstream/123456789/1999/1/The%20Data%20Revolution%20Big%20Data%2C%20Open%20Data%2C%20Data%20Infrastructures%20and%20Their%20Consequences%20by%20Rob%20Kitchin.pdf","citationUrl":"http://scholar.google.com/scholar?cites=13224876249693810802&as_sdt=2005&sciodt=0,5&hl=en","relatedUrl":"http://scholar.google.com/scholar?q=related:cvB_deEyiLcJ:scholar.google.com/&scioq=&hl=en&as_sdt=2005&sciodt=0,5","urlVersionsList":"http://scholar.google.com/scholar?cluster=13224876249693810802&hl=en&as_sdt=2005&sciodt=0,5","publication":"books.google.com","p":1,"exp":1596894386925},{"title":"Accelerating t-SNE using tree-based algorithms","url":"http://www.jmlr.org/papers/volume15/vandermaaten14a/vandermaaten14a.pdf","authors":["L Van Der Maaten"],"year":2014,"numCitations":1219,"pdf":"http://www.jmlr.org/papers/volume15/vandermaaten14a/vandermaaten14a.pdf","citationUrl":"http://scholar.google.com/scholar?cites=9031542969544004346&as_sdt=2005&sciodt=0,5&hl=en","relatedUrl":"http://scholar.google.com/scholar?q=related:-tJYyXp8Vn0J:scholar.google.com/&scioq=&hl=en&as_sdt=2005&sciodt=0,5","urlVersionsList":"http://scholar.google.com/scholar?cluster=9031542969544004346&hl=en&as_sdt=2005&sciodt=0,5","publication":"jmlr.org"},{"title":"Visualization of time-oriented data","url":"https://books.google.com/books?hl=en&lr=&id=YnDivwba2nkC&oi=fnd&pg=PR7&ots=7ooWaHH_zq&sig=LC_090_Q3hE_C4Jo8PznviNwHKM","authors":["W Aigner","W Aigner S Miksch","W Aigner S Miksch H Schumann","W Aigner S Miksch H Schumann C Tominski"],"year":2011,"numCitations":742,"pdf":"http://ieg.ifs.tuwien.ac.at/~aigner/timeviz-book/","citationUrl":"http://scholar.google.com/scholar?cites=12211193027499610440&as_sdt=2005&sciodt=0,5&hl=en","relatedUrl":"http://scholar.google.com/scholar?q=related:SFHXX1zfdqkJ:scholar.google.com/&scioq=&hl=en&as_sdt=2005&sciodt=0,5","urlVersionsList":"http://scholar.google.com/scholar?cluster=12211193027499610440&hl=en&as_sdt=2005&sciodt=0,5","publication":"books.google.com"},{"title":"Visualization and visual analysis of multifaceted scientific data: A survey","url":"https://ieeexplore.ieee.org/abstract/document/6185547/","authors":["J Kehrer","J Kehrer H Hauser"],"year":2012,"numCitations":328,"pdf":"http://www.multivis.net/draft.pdf","citationUrl":"http://scholar.google.com/scholar?cites=7783503225943925451&as_sdt=2005&sciodt=0,5&hl=en","relatedUrl":"http://scholar.google.com/scholar?q=related:y6J--vGOBGwJ:scholar.google.com/&scioq=&hl=en&as_sdt=2005&sciodt=0,5","urlVersionsList":"http://scholar.google.com/scholar?cluster=7783503225943925451&hl=en&as_sdt=2005&sciodt=0,5","publication":"ieeexplore.ieee.org"},{"title":"Towards fog-driven IoT eHealth: Promises and challenges of IoT in medicine and healthcare","url":"https://www.sciencedirect.com/science/article/pii/S0167739X17307677","authors":["B Farahani","B Farahani F Firouzi","B Farahani F Firouzi V Chang","B Farahani F Firouzi V Chang M Badaroglu…"],"year":2018,"numCitations":329,"pdf":"https://digitalcommons.uri.edu/cgi/viewcontent.cgi?article=1069&context=ele_facpubs","citationUrl":"http://scholar.google.com/scholar?cites=5031943308717220853&as_sdt=2005&sciodt=0,5&hl=en","relatedUrl":"http://scholar.google.com/scholar?q=related:9WP-ZccN1UUJ:scholar.google.com/&scioq=&hl=en&as_sdt=2005&sciodt=0,5","urlVersionsList":"http://scholar.google.com/scholar?cluster=5031943308717220853&hl=en&as_sdt=2005&sciodt=0,5","publication":"Elsevier"},{"title":"Interactive information visualization to explore and query electronic health records","url":"https://dl.acm.org/doi/abs/10.1561/1100000039","authors":["A Rind","A Rind TD Wang","A Rind TD Wang W Aigner","A Rind TD Wang W Aigner S Miksch…"],"year":2013,"numCitations":231,"pdf":"https://dl.acm.org/doi/abs/10.1561/1100000039","citationUrl":"http://scholar.google.com/scholar?cites=2646743229461192630&as_sdt=2005&sciodt=0,5&hl=en","relatedUrl":"http://scholar.google.com/scholar?q=related:tl-0s_EeuyQJ:scholar.google.com/&scioq=&hl=en&as_sdt=2005&sciodt=0,5","urlVersionsList":"http://scholar.google.com/scholar?cluster=2646743229461192630&hl=en&as_sdt=2005&sciodt=0,5","publication":"dl.acm.org"},{"title":"Knowledge generation model for visual analytics","url":"https://ieeexplore.ieee.org/abstract/document/6875967/","authors":["D Sacha","D Sacha A Stoffel","D Sacha A Stoffel F Stoffel","D Sacha A Stoffel F Stoffel BC Kwon…"],"year":2014,"numCitations":219,"pdf":"https://www.bckwon.com/pdf/kgva.pdf","citationUrl":"http://scholar.google.com/scholar?cites=7852739076111110539&as_sdt=2005&sciodt=0,5&hl=en","relatedUrl":"http://scholar.google.com/scholar?q=related:i5FuiZWI-mwJ:scholar.google.com/&scioq=&hl=en&as_sdt=2005&sciodt=0,5","urlVersionsList":"http://scholar.google.com/scholar?cluster=7852739076111110539&hl=en&as_sdt=2005&sciodt=0,5","publication":"ieeexplore.ieee.org"},{"title":"A survey of visual analytics techniques and applications: State-of-the-art research and future challenges","url":"https://link.springer.com/content/pdf/10.1007/s11390-013-1383-8.pdf","authors":["GD Sun","GD Sun YC Wu","GD Sun YC Wu RH Liang","GD Sun YC Wu RH Liang SX Liu"],"year":2013,"numCitations":181,"pdf":"http://citeseerx.ist.psu.edu/viewdoc/download?doi=10.1.1.496.5634&rep=rep1&type=pdf","citationUrl":"http://scholar.google.com/scholar?cites=18269634753658882032&as_sdt=2005&sciodt=0,5&hl=en","relatedUrl":"http://scholar.google.com/scholar?q=related:8Af4AwPIiv0J:scholar.google.com/&scioq=&hl=en&as_sdt=2005&sciodt=0,5","urlVersionsList":"http://scholar.google.com/scholar?cluster=18269634753658882032&hl=en&as_sdt=2005&sciodt=0,5","publication":"Springer"},{"title":"Visual analytics for the big data era—A comparative review of state-of-the-art commercial systems","url":"https://ieeexplore.ieee.org/abstract/document/6400554/","authors":["L Zhang","L Zhang A Stoffel","L Zhang A Stoffel M Behrisch…"],"year":2012,"numCitations":180,"pdf":"http://kops.uni-konstanz.de/bitstream/handle/123456789/22540/Zhang_225405.pdf?sequence=2","citationUrl":"http://scholar.google.com/scholar?cites=10417122926744547792&as_sdt=2005&sciodt=0,5&hl=en","relatedUrl":"http://scholar.google.com/scholar?q=related:0LEvDhwOkZAJ:scholar.google.com/&scioq=&hl=en&as_sdt=2005&sciodt=0,5","urlVersionsList":"http://scholar.google.com/scholar?cluster=10417122926744547792&hl=en&as_sdt=2005&sciodt=0,5","publication":"ieeexplore.ieee.org"},{"title":"Tap into visual analysis of customization of grouping of activities in eLearning","url":"https://www.sciencedirect.com/science/article/pii/S0747563214005779","authors":["DA Gómez"],"year":2015,"numCitations":170,"pdf":"https://www.researchgate.net/profile/Roberto_Theron/publication/269317478_Tap_into_visual_analysis_of_customization_of_grouping_of_activities_in_eLearning/links/5c168003a6fdcc494ffa14e8/Tap-into-visual-analysis-of-customization-of-grouping-of-activities-in-eLearning.pdf","citationUrl":"http://scholar.google.com/scholar?cites=7122213037530820891&as_sdt=2005&sciodt=0,5&hl=en","relatedUrl":"http://scholar.google.com/scholar?q=related:GzGuxAUv12IJ:scholar.google.com/&scioq=&hl=en&as_sdt=2005&sciodt=0,5","urlVersionsList":"http://scholar.google.com/scholar?cluster=7122213037530820891&hl=en&as_sdt=2005&sciodt=0,5","publication":"Elsevier"}]}