{"&cites=11512851231319557704&as_sdt=2005&sciodt=0,5&hl=en&scioq=geomagnetism":[{"title":"The rotation of the earth; a geophysical discussion","url":"https://ui.adsabs.harvard.edu/abs/1960regd.book.....M/abstract","authors":["WH Munk","WH Munk GJF MacDonald"],"year":1960,"numCitations":2119,"citationUrl":"http://scholar.google.com/scholar?cites=9082554740975067325&as_sdt=2005&sciodt=0,5&hl=en&scioq=geomagnetism","relatedUrl":"http://scholar.google.com/scholar?q=related:veDbXGq3C34J:scholar.google.com/&scioq=&hl=en&as_sdt=2005&sciodt=0,5","urlVersionsList":"http://scholar.google.com/scholar?cluster=9082554740975067325&hl=en&as_sdt=2005&sciodt=0,5&scioq=geomagnetism","publication":"ui.adsabs.harvard.edu","p":1,"exp":1596883461429},{"title":"The permeability of porous materials","url":"https://royalsocietypublishing.org/doi/abs/10.1098/rspa.1950.0068","authors":["EC Childs","EC Childs N Collis"],"year":1950,"numCitations":1308,"citationUrl":"http://scholar.google.com/scholar?cites=17431703460559503697&as_sdt=2005&sciodt=0,5&hl=en&scioq=geomagnetism","relatedUrl":"http://scholar.google.com/scholar?q=related:UcGYtPDZ6fEJ:scholar.google.com/&scioq=&hl=en&as_sdt=2005&sciodt=0,5","urlVersionsList":"http://scholar.google.com/scholar?cluster=17431703460559503697&hl=en&as_sdt=2005&sciodt=0,5&scioq=geomagnetism","publication":"royalsocietypublishing.org"},{"title":"The magnetic field of the earth: paleomagnetism, the core, and the deep mantle","url":"https://books.google.com/books?hl=en&lr=&id=96APl4nK9lIC&oi=fnd&pg=PR13&ots=O7g_s8P-6l&sig=qX_XG04fAo31-Rs2VqtIIULaTR0","authors":["MW McElhinny","MW McElhinny PL McFadden"],"year":1998,"numCitations":991,"citationUrl":"http://scholar.google.com/scholar?cites=4895855776234400483&as_sdt=2005&sciodt=0,5&hl=en&scioq=geomagnetism","relatedUrl":"http://scholar.google.com/scholar?q=related:4-r-neOS8UMJ:scholar.google.com/&scioq=&hl=en&as_sdt=2005&sciodt=0,5","urlVersionsList":"http://scholar.google.com/scholar?cluster=4895855776234400483&hl=en&as_sdt=2005&sciodt=0,5&scioq=geomagnetism","publication":"books.google.com"},{"title":"Homogeneous dynamos and terrestrial magnetism","url":"https://royalsocietypublishing.org/doi/abs/10.1098/rsta.1954.0018","authors":["EC Bullard","EC Bullard H Gellman"],"year":1954,"numCitations":774,"citationUrl":"http://scholar.google.com/scholar?cites=14915719015454624244&as_sdt=2005&sciodt=0,5&hl=en&scioq=geomagnetism","relatedUrl":"http://scholar.google.com/scholar?q=related:9Em27WpH_84J:scholar.google.com/&scioq=&hl=en&as_sdt=2005&sciodt=0,5","urlVersionsList":"http://scholar.google.com/scholar?cluster=14915719015454624244&hl=en&as_sdt=2005&sciodt=0,5&scioq=geomagnetism","publication":"royalsocietypublishing.org"},{"title":"Magneto-hydrodynamic shocks","url":"https://journals.aps.org/pr/abstract/10.1103/PhysRev.80.692","authors":["F De Hoffmann","F De Hoffmann E Teller"],"year":1950,"numCitations":739,"pdf":"http://ivanik3.narod.ru/Termojad/Gorjachiy/Hoffmann1950-80p692_1.pdf","citationUrl":"http://scholar.google.com/scholar?cites=14159403098321530739&as_sdt=2005&sciodt=0,5&hl=en&scioq=geomagnetism","relatedUrl":"http://scholar.google.com/scholar?q=related:cy8FIxlOgMQJ:scholar.google.com/&scioq=&hl=en&as_sdt=2005&sciodt=0,5","urlVersionsList":"http://scholar.google.com/scholar?cluster=14159403098321530739&hl=en&as_sdt=2005&sciodt=0,5&scioq=geomagnetism","publication":"APS"},{"title":"On the spontaneous magnetic field in a conducting liquid in turbulent motion","url":"https://royalsocietypublishing.org/doi/abs/10.1098/rspa.1950.0069","authors":["GK Batchelor"],"year":1950,"numCitations":517,"citationUrl":"http://scholar.google.com/scholar?cites=5902637661733426163&as_sdt=2005&sciodt=0,5&hl=en&scioq=geomagnetism","relatedUrl":"http://scholar.google.com/scholar?q=related:85N2Ca5h6lEJ:scholar.google.com/&scioq=&hl=en&as_sdt=2005&sciodt=0,5","urlVersionsList":"http://scholar.google.com/scholar?cluster=5902637661733426163&hl=en&as_sdt=2005&sciodt=0,5&scioq=geomagnetism","publication":"royalsocietypublishing.org"},{"title":"The westward drift of the Earth's magnetic field","url":"https://royalsocietypublishing.org/doi/abs/10.1098/rsta.1950.0014","authors":["EC Bullard","EC Bullard C Freedman…"],"year":1950,"numCitations":494,"citationUrl":"http://scholar.google.com/scholar?cites=13111954237488228941&as_sdt=2005&sciodt=0,5&hl=en&scioq=geomagnetism","relatedUrl":"http://scholar.google.com/scholar?q=related:TeqprOgE97UJ:scholar.google.com/&scioq=&hl=en&as_sdt=2005&sciodt=0,5","urlVersionsList":"http://scholar.google.com/scholar?cluster=13111954237488228941&hl=en&as_sdt=2005&sciodt=0,5&scioq=geomagnetism","publication":"royalsocietypublishing.org"},{"title":"Oscillations of a system of disk dynamos","url":"https://www.cambridge.org/core/services/aop-cambridge-core/content/view/S0305004100033223","authors":["T Rikitake"],"year":1958,"numCitations":478,"citationUrl":"http://scholar.google.com/scholar?cites=1821391017617336734&as_sdt=2005&sciodt=0,5&hl=en&scioq=geomagnetism","relatedUrl":"http://scholar.google.com/scholar?q=related:nikr-nrhRhkJ:scholar.google.com/&scioq=&hl=en&as_sdt=2005&sciodt=0,5","urlVersionsList":"http://scholar.google.com/scholar?cluster=1821391017617336734&hl=en&as_sdt=2005&sciodt=0,5&scioq=geomagnetism","publication":"cambridge.org"},{"title":"Electromagnetism and the Earth's Interior","url":"https://books.google.com/books?hl=en&lr=&id=zl7B1XjLZn8C&oi=fnd&pg=PP1&ots=0cK0u-rth2&sig=QjQu-TqAvH33ougqek8VocC3vxw","authors":["T Rikitake"],"year":2012,"numCitations":407,"citationUrl":"http://scholar.google.com/scholar?cites=7235388742523446939&as_sdt=2005&sciodt=0,5&hl=en&scioq=geomagnetism","relatedUrl":"http://scholar.google.com/scholar?q=related:m2b4AbpDaWQJ:scholar.google.com/&scioq=&hl=en&as_sdt=2005&sciodt=0,5","urlVersionsList":"http://scholar.google.com/scholar?cluster=7235388742523446939&hl=en&as_sdt=2005&sciodt=0,5&scioq=geomagnetism","publication":"books.google.com"},{"title":"Electromagnetic effects–From cell biology to medicine","url":"https://www.sciencedirect.com/science/article/pii/S0079633608000375","authors":["RHW Funk","RHW Funk T Monsees","RHW Funk T Monsees N Özkucur"],"year":2009,"numCitations":407,"pdf":"https://www.researchgate.net/profile/Richard_Funk/publication/6981003_Effects_of_Electromagnetic_Fields_on_Cells_Physiological_and_Therapeutical_Approaches_and_Molecular_Mechanisms_of_Interaction/links/548016680cf25b80dd703e9b.pdf","citationUrl":"http://scholar.google.com/scholar?cites=18171668571233278987&as_sdt=2005&sciodt=0,5&hl=en&scioq=geomagnetism","relatedUrl":"http://scholar.google.com/scholar?q=related:C1x9tEm8LvwJ:scholar.google.com/&scioq=&hl=en&as_sdt=2005&sciodt=0,5","urlVersionsList":"http://scholar.google.com/scholar?cluster=18171668571233278987&hl=en&as_sdt=2005&sciodt=0,5&scioq=geomagnetism","publication":"Elsevier"}]}