{"&cites=13383209234190047008&as_sdt=2005&sciodt=0,5&hl=en":[{"title":"An introduction to political communication","url":"https://books.google.com/books?hl=en&lr=&id=4kwrDwAAQBAJ&oi=fnd&pg=PP1&ots=_gpwSLbRYH&sig=Z0gdDN99hrWOP3TzakSIGt0Wacc","authors":["B McNair"],"year":2017,"numCitations":2426,"pdf":"http://repository.fue.edu.eg/xmlui/bitstream/handle/123456789/3659/10310.pdf?sequence=1","citationUrl":"http://scholar.google.com/scholar?cites=11661887232193076696&as_sdt=2005&sciodt=0,5&hl=en","relatedUrl":"http://scholar.google.com/scholar?q=related:2B2IfaZY16EJ:scholar.google.com/&scioq=&hl=en&as_sdt=2005&sciodt=0,5","urlVersionsList":"http://scholar.google.com/scholar?cluster=11661887232193076696&hl=en&as_sdt=2005&sciodt=0,5","publication":"books.google.com","p":1,"exp":1596891834503},{"title":"News culture","url":"https://books.google.com/books?hl=en&lr=&id=lvlEBgAAQBAJ&oi=fnd&pg=PP1&ots=ih8E5B3Ka2&sig=6v3E8Kfeu4nlrRIV38wdtSI5ZtY","authors":["S Allan"],"year":2010,"numCitations":1134,"citationUrl":"http://scholar.google.com/scholar?cites=13817937559763924758&as_sdt=2005&sciodt=0,5&hl=en","relatedUrl":"http://scholar.google.com/scholar?q=related:FrdBAgAtw78J:scholar.google.com/&scioq=&hl=en&as_sdt=2005&sciodt=0,5","urlVersionsList":"http://scholar.google.com/scholar?cluster=13817937559763924758&hl=en&as_sdt=2005&sciodt=0,5","publication":"books.google.com"},{"title":"Embodying Nationhood? Conceptions of British national identity, citizenship, and Gender in the 'Veil Affair'","url":"https://journals.sagepub.com/doi/abs/10.1111/j.1467-954X.2009.01877.x","authors":["N Meer","N Meer C Dwyer","N Meer C Dwyer T Modood"],"year":2010,"numCitations":159,"pdf":"https://journals.sagepub.com/doi/pdf/10.1111/j.1467-954X.2009.01877.x","citationUrl":"http://scholar.google.com/scholar?cites=16197261069760739260&as_sdt=2005&sciodt=0,5&hl=en","relatedUrl":"http://scholar.google.com/scholar?q=related:vDdaTSA7yOAJ:scholar.google.com/&scioq=&hl=en&as_sdt=2005&sciodt=0,5","urlVersionsList":"http://scholar.google.com/scholar?cluster=16197261069760739260&hl=en&as_sdt=2005&sciodt=0,5","publication":"journals.sagepub.com"},{"title":"Slutwalk: Feminism, activism and media","url":"https://books.google.com/books?hl=en&lr=&id=JFEMCgAAQBAJ&oi=fnd&pg=PP1&ots=7UpIwjDSjx&sig=eRwhYM4DP23JLOEG-UAHYHE1E1M","authors":["K Mendes"],"year":2015,"numCitations":117,"citationUrl":"http://scholar.google.com/scholar?cites=820401519456594315&as_sdt=2005&sciodt=0,5&hl=en","relatedUrl":"http://scholar.google.com/scholar?q=related:i6lm1NWmYgsJ:scholar.google.com/&scioq=&hl=en&as_sdt=2005&sciodt=0,5","urlVersionsList":"http://scholar.google.com/scholar?cluster=820401519456594315&hl=en&as_sdt=2005&sciodt=0,5","publication":"books.google.com"},{"title":"Newspaper journalism","url":"https://books.google.com/books?hl=en&lr=&id=QndhVvGQnSQC&oi=fnd&pg=PP2&ots=VuDGQl3-OO&sig=lYsjFxgW_T9V7XG1qc1jmyLWp-U","authors":["P Cole","P Cole T Harcup"],"year":2009,"numCitations":101,"pdf":"http://web2.bilkent.edu.tr/wp-content/uploads/sites/37/2017/02/Peter_Cole_and_Tony_Harcup_Newspaper_JournalismBookFi.org_.pdf","citationUrl":"http://scholar.google.com/scholar?cites=16129351906245321663&as_sdt=2005&sciodt=0,5&hl=en","relatedUrl":"http://scholar.google.com/scholar?q=related:v6MFDRr41t8J:scholar.google.com/&scioq=&hl=en&as_sdt=2005&sciodt=0,5","urlVersionsList":"http://scholar.google.com/scholar?cluster=16129351906245321663&hl=en&as_sdt=2005&sciodt=0,5","publication":"books.google.com"},{"title":"Between decline and a new online business model: The case of the Spanish newspaper industry","url":"https://www.tandfonline.com/doi/abs/10.1080/16522354.2013.11073560","authors":["A Casero"],"year":2013,"numCitations":73,"pdf":"http://repositori.uji.es/xmlui/bitstream/handle/10234/92211/Casero_Izquierdo.pdf?sequence=1&isAllowed=y","citationUrl":"http://scholar.google.com/scholar?cites=14263594891721334373&as_sdt=2005&sciodt=0,5&hl=en","relatedUrl":"http://scholar.google.com/scholar?q=related:ZV4gdft38sUJ:scholar.google.com/&scioq=&hl=en&as_sdt=2005&sciodt=0,5","urlVersionsList":"http://scholar.google.com/scholar?cluster=14263594891721334373&hl=en&as_sdt=2005&sciodt=0,5","publication":"Taylor & Francis"},{"title":"Crime news in modern Britain: Press reporting and responsibility, 1820-2010","url":"https://books.google.com/books?hl=en&lr=&id=VfbRAQAAQBAJ&oi=fnd&pg=PP1&ots=Uc7vWAg_uq&sig=KXK8fagsT11oOC3bg7kcckbFSC0","authors":["J Rowbotham","J Rowbotham K Stevenson","J Rowbotham K Stevenson S Pegg"],"year":2013,"numCitations":46,"citationUrl":"http://scholar.google.com/scholar?cites=18261458075173138581&as_sdt=2005&sciodt=0,5&hl=en","relatedUrl":"http://scholar.google.com/scholar?q=related:lTBis127bf0J:scholar.google.com/&scioq=&hl=en&as_sdt=2005&sciodt=0,5","urlVersionsList":"http://scholar.google.com/scholar?cluster=18261458075173138581&hl=en&as_sdt=2005&sciodt=0,5","publication":"books.google.com"},{"title":"The regional‐newspaper industry supply chain and the internet","url":"https://www.emerald.com/insight/content/doi/10.1108/13598541011039956/full/html","authors":["G Graham","G Graham A Smart"],"year":2010,"numCitations":43,"citationUrl":"http://scholar.google.com/scholar?cites=13456589437661249923&as_sdt=2005&sciodt=0,5&hl=en","relatedUrl":"http://scholar.google.com/scholar?q=related:g4ESKMxov7oJ:scholar.google.com/&scioq=&hl=en&as_sdt=2005&sciodt=0,5","urlVersionsList":"http://scholar.google.com/scholar?cluster=13456589437661249923&hl=en&as_sdt=2005&sciodt=0,5","publication":"emerald.com"},{"title":"Hyper-local news: A glue to hold rural communities together?","url":"https://journals.sagepub.com/doi/abs/10.1177/0269094211428860","authors":["D Baines"],"year":2012,"numCitations":33,"pdf":"http://citeseerx.ist.psu.edu/viewdoc/download?doi=10.1.1.1023.6963&rep=rep1&type=pdf","citationUrl":"http://scholar.google.com/scholar?cites=8814359898910366362&as_sdt=2005&sciodt=0,5&hl=en","relatedUrl":"http://scholar.google.com/scholar?q=related:mhoAqaDlUnoJ:scholar.google.com/&scioq=&hl=en&as_sdt=2005&sciodt=0,5","urlVersionsList":"http://scholar.google.com/scholar?cluster=8814359898910366362&hl=en&as_sdt=2005&sciodt=0,5","publication":"journals.sagepub.com"}]}