{"&cites=7642659266312510011&as_sdt=2005&sciodt=0,5&hl=en":[{"title":"Computational principles of mobile robotics","url":"https://books.google.com/books?hl=en&lr=&id=db5pr2275i0C&oi=fnd&pg=PR7&ots=_C5L41hYUT&sig=onmnKWvt7FnNGvnAI4Qo0Ws-JK4","authors":["G Dudek","G Dudek M Jenkin"],"year":2010,"numCitations":1347,"citationUrl":"http://scholar.google.com/scholar?cites=5646452653535207939&as_sdt=2005&sciodt=0,5&hl=en","relatedUrl":"http://scholar.google.com/scholar?q=related:AyIHr8U6XE4J:scholar.google.com/&scioq=&hl=en&as_sdt=2005&sciodt=0,5","urlVersionsList":"http://scholar.google.com/scholar?cluster=5646452653535207939&hl=en&as_sdt=2005&sciodt=0,5","publication":"books.google.com","p":1,"exp":1596368510666},{"title":"Small unmanned aircraft: Theory and practice","url":"https://books.google.com/books?hl=en&lr=&id=YqQtjhPUaNEC&oi=fnd&pg=PP1&ots=yydCGGxFOb&sig=7Dsyjk33eMujskSidKGLPcV-b9s","authors":["RW Beard","RW Beard TW McLain"],"year":2012,"numCitations":943,"citationUrl":"http://scholar.google.com/scholar?cites=1223243753587130522&as_sdt=2005&sciodt=0,5&hl=en","relatedUrl":"http://scholar.google.com/scholar?q=related:msBGfrbV-RAJ:scholar.google.com/&scioq=&hl=en&as_sdt=2005&sciodt=0,5","urlVersionsList":"http://scholar.google.com/scholar?cluster=1223243753587130522&hl=en&as_sdt=2005&sciodt=0,5","publication":"books.google.com"},{"title":"Introduction to aircraft aeroelasticity and loads","url":"https://books.google.com/books?hl=en&lr=&id=BU_tRQaz9gIC&oi=fnd&pg=PR7&ots=9_9T3FsCmm&sig=vuf7LHvy4c6RcqamB0C33saD-SA","authors":["JR Wright","JR Wright JE Cooper"],"year":2008,"numCitations":727,"pdf":"https://www.academia.edu/download/55091093/7.-Introduction-Aircraft-Aeroelasticity-and-Load.pdf","citationUrl":"http://scholar.google.com/scholar?cites=5605252840602267561&as_sdt=2005&sciodt=0,5&hl=en","relatedUrl":"http://scholar.google.com/scholar?q=related:qe9YuMLbyU0J:scholar.google.com/&scioq=&hl=en&as_sdt=2005&sciodt=0,5","urlVersionsList":"http://scholar.google.com/scholar?cluster=5605252840602267561&hl=en&as_sdt=2005&sciodt=0,5","publication":"books.google.com"},{"title":"Modeling and identification of linear parameter-varying systems","url":"https://books.google.com/books?hl=en&lr=&id=dh1uCQAAQBAJ&oi=fnd&pg=PR3&ots=1AzLlZTwua&sig=uYgCS6Gx1clBi8a2cPcUQjQJ0dI","authors":["R Tóth"],"year":2010,"numCitations":429,"citationUrl":"http://scholar.google.com/scholar?cites=15560454204056588450&as_sdt=2005&sciodt=0,5&hl=en","relatedUrl":"http://scholar.google.com/scholar?q=related:otCG4KfW8dcJ:scholar.google.com/&scioq=&hl=en&as_sdt=2005&sciodt=0,5","urlVersionsList":"http://scholar.google.com/scholar?cluster=15560454204056588450&hl=en&as_sdt=2005&sciodt=0,5","publication":"books.google.com"},{"title":"Sensory systems and flight stability: what do insects measure and why?","url":"https://www.sciencedirect.com/science/article/pii/S0065280607340058","authors":["GK Taylor","GK Taylor HG Krapp"],"year":2007,"numCitations":247,"citationUrl":"http://scholar.google.com/scholar?cites=8533257269591193307&as_sdt=2005&sciodt=0,5&hl=en","relatedUrl":"http://scholar.google.com/scholar?q=related:27YAi0Y4bHYJ:scholar.google.com/&scioq=&hl=en&as_sdt=2005&sciodt=0,5","urlVersionsList":"http://scholar.google.com/scholar?cluster=8533257269591193307&hl=en&as_sdt=2005&sciodt=0,5","publication":"Elsevier"},{"title":"Dynamic flight stability in the desert locust Schistocerca gregaria","url":"https://jeb.biologists.org/content/206/16/2803.short","authors":["GK Taylor","GK Taylor ALR Thomas"],"year":2003,"numCitations":247,"pdf":"https://jeb.biologists.org/content/jexbio/206/16/2803.full.pdf?download=true","citationUrl":"http://scholar.google.com/scholar?cites=13496817086722615658&as_sdt=2005&sciodt=0,5&hl=en","relatedUrl":"http://scholar.google.com/scholar?q=related:aimGlKFTTrsJ:scholar.google.com/&scioq=&hl=en&as_sdt=2005&sciodt=0,5","urlVersionsList":"http://scholar.google.com/scholar?cluster=13496817086722615658&hl=en&as_sdt=2005&sciodt=0,5","publication":"jeb.biologists.org"},{"title":"A prototype of an autonomous controller for a quadrotor UAV","url":"https://ieeexplore.ieee.org/abstract/document/7068316/","authors":["ID Cowling","ID Cowling OA Yakimenko…"],"year":2007,"numCitations":199,"pdf":"https://dspace.lib.cranfield.ac.uk/bitstream/handle/1826/14061/Prototype_of_Autonomous_Controller_2007.pdf?sequence=1&isAllowed=y","citationUrl":"http://scholar.google.com/scholar?cites=17242033212935919657&as_sdt=2005&sciodt=0,5&hl=en","relatedUrl":"http://scholar.google.com/scholar?q=related:KViI3toBSO8J:scholar.google.com/&scioq=&hl=en&as_sdt=2005&sciodt=0,5","urlVersionsList":"http://scholar.google.com/scholar?cluster=17242033212935919657&hl=en&as_sdt=2005&sciodt=0,5","publication":"ieeexplore.ieee.org"},{"title":"Mechanics and aerodynamics of insect flight control","url":"https://onlinelibrary.wiley.com/doi/abs/10.1017/S1464793101005759","authors":["GK Taylor"],"year":2001,"numCitations":189,"citationUrl":"http://scholar.google.com/scholar?cites=16398755718808494812&as_sdt=2005&sciodt=0,5&hl=en","relatedUrl":"http://scholar.google.com/scholar?q=related:3GL8IXEVlOMJ:scholar.google.com/&scioq=&hl=en&as_sdt=2005&sciodt=0,5","urlVersionsList":"http://scholar.google.com/scholar?cluster=16398755718808494812&hl=en&as_sdt=2005&sciodt=0,5","publication":"Wiley Online Library"},{"title":"Applications of the unsteady vortex-lattice method in aircraft aeroelasticity and flight dynamics","url":"https://www.sciencedirect.com/science/article/pii/S0376042112000620","authors":["J Murua","J Murua R Palacios","J Murua R Palacios JMR Graham"],"year":2012,"numCitations":154,"pdf":"http://epubs.surrey.ac.uk/795747/3/J04@%20Murua,%20Palacios%20%26%20Graham%20(PAS,%202012)%20Applications%20of%20the%20unsteady%20vortex-lattice%20method%20in%20aircraft%20aeroelasticity%20and%20flight%20dynamics.pdf","citationUrl":"http://scholar.google.com/scholar?cites=15333997262596335245&as_sdt=2005&sciodt=0,5&hl=en","relatedUrl":"http://scholar.google.com/scholar?q=related:jebdb0RNzdQJ:scholar.google.com/&scioq=&hl=en&as_sdt=2005&sciodt=0,5","urlVersionsList":"http://scholar.google.com/scholar?cluster=15333997262596335245&hl=en&as_sdt=2005&sciodt=0,5","publication":"Elsevier"},{"title":"A stability guaranteed active fault‐tolerant control system against actuator failures","url":"https://onlinelibrary.wiley.com/doi/abs/10.1002/rnc.932","authors":["M Maki","M Maki J Jiang","M Maki J Jiang K Hagino"],"year":2004,"numCitations":141,"citationUrl":"http://scholar.google.com/scholar?cites=17309389279782762126&as_sdt=2005&sciodt=0,5&hl=en","relatedUrl":"http://scholar.google.com/scholar?q=related:jvZnRNdNN_AJ:scholar.google.com/&scioq=&hl=en&as_sdt=2005&sciodt=0,5","urlVersionsList":"http://scholar.google.com/scholar?cluster=17309389279782762126&hl=en&as_sdt=2005&sciodt=0,5","publication":"Wiley Online Library"}]}