{"&cites=2511964840346198274&as_sdt=2005&sciodt=0,5&hl=en":[{"title":"Institutions and organizations","url":"http://citeseerx.ist.psu.edu/viewdoc/summary?doi=10.1.1.602.4986","authors":["SM Scott"],"year":1995,"numCitations":22102,"citationUrl":"http://scholar.google.com/scholar?cites=3051412648745172220&as_sdt=2005&sciodt=0,5&hl=en","relatedUrl":"http://scholar.google.com/scholar?q=related:_PyWD6PLWCoJ:scholar.google.com/&scioq=&hl=en&as_sdt=2005&sciodt=0,5","publication":"Citeseer","p":1,"exp":1596885499837},{"title":"Strategic responses to institutional processes","url":"https://journals.aom.org/doi/abs/10.5465/AMR.1991.4279002","authors":["C Oliver"],"year":1991,"numCitations":10512,"pdf":"http://citeseerx.ist.psu.edu/viewdoc/download?doi=10.1.1.468.3856&rep=rep1&type=pdf","citationUrl":"http://scholar.google.com/scholar?cites=6727164658483202441&as_sdt=2005&sciodt=0,5&hl=en","relatedUrl":"http://scholar.google.com/scholar?q=related:iQl0Zp2wW10J:scholar.google.com/&scioq=&hl=en&as_sdt=2005&sciodt=0,5","urlVersionsList":"http://scholar.google.com/scholar?cluster=6727164658483202441&hl=en&as_sdt=2005&sciodt=0,5","publication":"journals.aom.org"},{"title":"Managing legitimacy: Strategic and institutional approaches","url":"https://journals.aom.org/doi/abs/10.5465/AMR.1995.9508080331","authors":["MC Suchman"],"year":1995,"numCitations":16696,"pdf":"https://www.sabin.org/sites/sabin.org/files/restricted/Suchman_legitimacy_95.pdf","citationUrl":"http://scholar.google.com/scholar?cites=14855847139247338215&as_sdt=2005&sciodt=0,5&hl=en","relatedUrl":"http://scholar.google.com/scholar?q=related:5zJXdEOSKs4J:scholar.google.com/&scioq=&hl=en&as_sdt=2005&sciodt=0,5","urlVersionsList":"http://scholar.google.com/scholar?cluster=14855847139247338215&hl=en&as_sdt=2005&sciodt=0,5","publication":"journals.aom.org"},{"title":"The mechanisms of governance","url":"https://books.google.com/books?hl=en&lr=&id=9cfQCwAAQBAJ&oi=fnd&pg=PR11&ots=lnsc13s-hZ&sig=a0S5XpKB9hZ7_KlTgI7P12ml7aQ","authors":["OE Williamson"],"year":1996,"numCitations":9488,"citationUrl":"http://scholar.google.com/scholar?cites=18391690989668203448&as_sdt=2005&sciodt=0,5&hl=en","relatedUrl":"http://scholar.google.com/scholar?q=related:uPvsAYNpPP8J:scholar.google.com/&scioq=&hl=en&as_sdt=2005&sciodt=0,5","urlVersionsList":"http://scholar.google.com/scholar?cluster=18391690989668203448&hl=en&as_sdt=2005&sciodt=0,5","publication":"books.google.com"},{"title":"Institutions and organizations: Ideas, interests, and identities","url":"https://books.google.com/books?hl=en&lr=&id=NbQgAQAAQBAJ&oi=fnd&pg=PP1&ots=hFXdeIpf1F&sig=sZg_f7gear3qopONQQg6gj5eJfQ","authors":["WR Scott"],"year":2013,"numCitations":7716,"citationUrl":"http://scholar.google.com/scholar?cites=1744551422073878375&as_sdt=2005&sciodt=0,5&hl=en","relatedUrl":"http://scholar.google.com/scholar?q=related:Z7cdfUbkNRgJ:scholar.google.com/&scioq=&hl=en&as_sdt=2005&sciodt=0,5","urlVersionsList":"http://scholar.google.com/scholar?cluster=1744551422073878375&hl=en&as_sdt=2005&sciodt=0,5","publication":"books.google.com"},{"title":"Historical institutionalism in comparative politics","url":"https://www.annualreviews.org/doi/abs/10.1146/annurev.polisci.2.1.369","authors":["K Thelen"],"year":1999,"numCitations":6978,"pdf":"https://www.academia.edu/download/29897530/thelan_1999.pdf","citationUrl":"http://scholar.google.com/scholar?cites=17417417382980796578&as_sdt=2005&sciodt=0,5&hl=en","relatedUrl":"http://scholar.google.com/scholar?q=related:osBIEdQYt_EJ:scholar.google.com/&scioq=&hl=en&as_sdt=2005&sciodt=0,5","urlVersionsList":"http://scholar.google.com/scholar?cluster=17417417382980796578&hl=en&as_sdt=2005&sciodt=0,5","publication":"annualreviews.org"},{"title":"Organization theory: Modern, symbolic, and postmodern perspectives","url":"https://books.google.com/books?hl=en&lr=&id=L2pNDwAAQBAJ&oi=fnd&pg=PP1&ots=6PWUxaJrRM&sig=prmX-cMptVNpIxXAVbVaP_sTGcA","authors":["MJ Hatch"],"year":2018,"numCitations":6580,"citationUrl":"http://scholar.google.com/scholar?cites=3633183963599005492&as_sdt=2005&sciodt=0,5&hl=en","relatedUrl":"http://scholar.google.com/scholar?q=related:NOf2wZCpazIJ:scholar.google.com/&scioq=&hl=en&as_sdt=2005&sciodt=0,5","urlVersionsList":"http://scholar.google.com/scholar?cluster=3633183963599005492&hl=en&as_sdt=2005&sciodt=0,5","publication":"books.google.com"},{"title":"World society and the nation-state","url":"https://www.journals.uchicago.edu/doi/abs/10.1086/231174","authors":["JW Meyer","JW Meyer J Boli","JW Meyer J Boli GM Thomas…"],"year":1997,"numCitations":5605,"pdf":"http://prelim2009.filmbulletin.org/readings/06-Political_Sociology/Meyer.pdf","citationUrl":"http://scholar.google.com/scholar?cites=3539009439542137992&as_sdt=2005&sciodt=0,5&hl=en","relatedUrl":"http://scholar.google.com/scholar?q=related:iNSptFUWHTEJ:scholar.google.com/&scioq=&hl=en&as_sdt=2005&sciodt=0,5","urlVersionsList":"http://scholar.google.com/scholar?cluster=3539009439542137992&hl=en&as_sdt=2005&sciodt=0,5","publication":"journals.uchicago.edu"},{"title":"The narrative constitution of identity: A relational and network approach","url":"https://link.springer.com/content/pdf/10.1007/BF00992905.pdf","authors":["MR Somers"],"year":1994,"numCitations":3628,"pdf":"https://deepblue.lib.umich.edu/bitstream/handle/2027.42/43649/11186_2004_Article_BF00992905.pdf?sequence=1","citationUrl":"http://scholar.google.com/scholar?cites=14220020577745982129&as_sdt=2005&sciodt=0,5&hl=en","relatedUrl":"http://scholar.google.com/scholar?q=related:sVJL41-pV8UJ:scholar.google.com/&scioq=&hl=en&as_sdt=2005&sciodt=0,5","urlVersionsList":"http://scholar.google.com/scholar?cluster=14220020577745982129&hl=en&as_sdt=2005&sciodt=0,5","publication":"Springer"},{"title":"Culture and cognition","url":"https://www.annualreviews.org/doi/abs/10.1146/annurev.soc.23.1.263","authors":["P DiMaggio"],"year":1997,"numCitations":3558,"pdf":"http://disciplinas.stoa.usp.br/pluginfile.php/360972/mod_resource/content/1/dimaggio_culturecognition_1997.pdf","citationUrl":"http://scholar.google.com/scholar?cites=844277219682106359&as_sdt=2005&sciodt=0,5&hl=en","relatedUrl":"http://scholar.google.com/scholar?q=related:9zsbe6h5twsJ:scholar.google.com/&scioq=&hl=en&as_sdt=2005&sciodt=0,5","urlVersionsList":"http://scholar.google.com/scholar?cluster=844277219682106359&hl=en&as_sdt=2005&sciodt=0,5","publication":"annualreviews.org"}]}