{"&cites=2603364325375332883&as_sdt=2005&sciodt=0,5&hl=en":[{"title":"Reaching and Retaining American-Born Asian Millennials at Bay Area Chinese Bible Church","url":"http://search.proquest.com/openview/08f3cad141fd63ae2d409a4a0371473e/1?pq-origsite=gscholar&cbl=18750&diss=y","authors":["SG Quen"],"year":2018,"numCitations":2,"citationUrl":"http://scholar.google.com/scholar?cites=10968821707151899980&as_sdt=2005&sciodt=0,5&hl=en","relatedUrl":"http://scholar.google.com/scholar?q=related:TP1hMzoVOZgJ:scholar.google.com/&scioq=&hl=en&as_sdt=2005&sciodt=0,5","publication":"search.proquest.com","p":1,"exp":1596881753795},{"title":"Helping English pastors to be more culturally sensitive in Canadian Chinese churches","url":"http://search.proquest.com/openview/5c68a7abd6303ce33b5e8c419253c7bb/1?pq-origsite=gscholar&cbl=18750&diss=y","authors":["JCS Ching"],"year":2017,"numCitations":1,"citationUrl":"http://scholar.google.com/scholar?cites=13590175959448819298&as_sdt=2005&sciodt=0,5&hl=en","relatedUrl":"http://scholar.google.com/scholar?q=related:YhYAAggBmrwJ:scholar.google.com/&scioq=&hl=en&as_sdt=2005&sciodt=0,5","publication":"search.proquest.com"},{"title":"Reading Romans with Eastern Eyes: Honor and Shame in Paul's Message and Mission","url":"https://books.google.com/books?hl=en&lr=&id=v6GMDwAAQBAJ&oi=fnd&pg=PP1&ots=Tc83eugudq&sig=0sKvtTR21J1rGwr4-_6vtLZWb0g","authors":["W Jackson"],"year":2019,"numCitations":2,"citationUrl":"http://scholar.google.com/scholar?cites=16348747703620535613&as_sdt=2005&sciodt=0,5&hl=en","relatedUrl":"http://scholar.google.com/scholar?q=related:PQXJxGpr4uIJ:scholar.google.com/&scioq=&hl=en&as_sdt=2005&sciodt=0,5","publication":"books.google.com"},{"title":"Contextualizing the Gospel for Southeast Asian Buddhists: Recovering the Critical Themes of Kingdom and Covenant in Evangelism","url":"http://search.proquest.com/openview/9e27d6f009674235a93b85f544d9fd4e/1?pq-origsite=gscholar&cbl=18750&diss=y","authors":["EC Mullis"],"year":2018,"numCitations":0,"pdf":"http://search.proquest.com/openview/9e27d6f009674235a93b85f544d9fd4e/1?pq-origsite=gscholar&cbl=18750&diss=y","relatedUrl":"http://scholar.google.com/scholar?q=related:DWRzQ0z1S28J:scholar.google.com/&scioq=&hl=en&as_sdt=2005&sciodt=0,5","publication":"search.proquest.com"},{"title":"The Impact of A Christian Spiritual Formation Program on Chinese Students at A North American Seminary","url":"http://search.proquest.com/openview/b07a90038bb7face5f59003b4726421b/1?pq-origsite=gscholar&cbl=18750&diss=y","authors":["D Wang"],"year":2020,"numCitations":0,"relatedUrl":"http://scholar.google.com/scholar?q=related:NBMBaDReQvIJ:scholar.google.com/&scioq=&hl=en&as_sdt=2005&sciodt=0,5","publication":"search.proquest.com"},{"title":"How Cultural Reciprocity Practices Reinforce Merit-Making Affecting the Experience of God's Grace","url":"https://books.google.com/books?hl=en&lr=&id=s-tFDwAAQBAJ&oi=fnd&pg=PA155&ots=0qdcdh-EAK&sig=p3b7W10HIs4AN3Ey_XBO4-NCt24","authors":["ST Silzer"],"year":2017,"numCitations":0,"relatedUrl":"http://scholar.google.com/scholar?q=related:ETbbmH6Ftn4J:scholar.google.com/&scioq=&hl=en&as_sdt=2005&sciodt=0,5","urlVersionsList":"http://scholar.google.com/scholar?cluster=9130632073317135889&hl=en&as_sdt=2005&sciodt=0,5","publication":"books.google.com"},{"title":"CHINESE ANCESTOR WORSHIP AND CHRISTIANITY: A HISTORICAL AND CONTEXTUAL EVALUATION","url":"http://www.academia.edu/download/58255096/CHINESE_ANCESTOR_WORSHIP_AND_CHRISTIANITY_FINAL.pdf","authors":["CG Fobes"],"year":2018,"numCitations":0,"pdf":"http://www.academia.edu/download/58255096/CHINESE_ANCESTOR_WORSHIP_AND_CHRISTIANITY_FINAL.pdf","relatedUrl":"http://scholar.google.com/scholar?q=related:eJa5qr5C1T8J:scholar.google.com/&scioq=&hl=en&as_sdt=2005&sciodt=0,5","urlVersionsList":"http://scholar.google.com/scholar?cluster=4599655981104338552&hl=en&as_sdt=2005&sciodt=0,5","publication":"academia.edu"},{"title":"Exploring How Shame Affects Asian Americans in the Classroom","url":"https://www.tandfonline.com/doi/abs/10.1080/15363759.2019.1633832","authors":["G Ng"],"year":2019,"numCitations":0,"relatedUrl":"http://scholar.google.com/scholar?q=related:S5dPxVuBCC4J:scholar.google.com/&scioq=&hl=en&as_sdt=2005&sciodt=0,5","urlVersionsList":"http://scholar.google.com/scholar?cluster=3317043356710704971&hl=en&as_sdt=2005&sciodt=0,5","publication":"Taylor & Francis"},{"title":"A Culture of Reconciliation as a Key Catalyst for a Thriving Asian North American Church","url":"https://www.academia.edu/download/53704962/IM501-ResearchPaper_CSun_edited-ACAD.pdf","authors":["C Sun"],"year":0,"numCitations":0,"pdf":"https://www.academia.edu/download/53704962/IM501-ResearchPaper_CSun_edited-ACAD.pdf","relatedUrl":"http://scholar.google.com/scholar?q=related:SHetyLIl3MAJ:scholar.google.com/&scioq=&hl=en&as_sdt=2005&sciodt=0,5","urlVersionsList":"http://scholar.google.com/scholar?cluster=13897023999959725896&hl=en&as_sdt=2005&sciodt=0,5","publication":"academia.edu"},{"title":"Cognitive Issues in Bible Translation: The Biblical Text in the Context of Human Experience","url":"https://journals.sagepub.com/doi/abs/10.1177/2051677020907676","authors":["RD Shaw","RD Shaw D DeLoach","RD Shaw D DeLoach J Grimes…"],"year":2020,"numCitations":0,"relatedUrl":"http://scholar.google.com/scholar?q=related:0DM9yte86eQJ:scholar.google.com/&scioq=&hl=en&as_sdt=2005&sciodt=0,5","publication":"journals.sagepub.com"}]}