{"&cites=17769015407974247969&as_sdt=2005&sciodt=0,5&hl=en":[{"title":"Overview of current development in electrical energy storage technologies and the application potential in power system operation","url":"https://www.sciencedirect.com/science/article/pii/S0306261914010290","authors":["X Luo","X Luo J Wang","X Luo J Wang M Dooner","X Luo J Wang M Dooner J Clarke"],"year":2015,"numCitations":2089,"pdf":"https://www.sciencedirect.com/science/article/pii/S0306261914010290","citationUrl":"http://scholar.google.com/scholar?cites=11417818656558468737&as_sdt=2005&sciodt=0,5&hl=en","relatedUrl":"http://scholar.google.com/scholar?q=related:gc7-7ZI9dJ4J:scholar.google.com/&scioq=&hl=en&as_sdt=2005&sciodt=0,5","urlVersionsList":"http://scholar.google.com/scholar?cluster=11417818656558468737&hl=en&as_sdt=2005&sciodt=0,5","publication":"Elsevier","p":1,"exp":1596367111290},{"title":"A review of energy storage technologies for wind power applications","url":"https://www.sciencedirect.com/science/article/pii/S1364032112000305","authors":["F Díaz"],"year":2012,"numCitations":1227,"citationUrl":"http://scholar.google.com/scholar?cites=16461024828027076035&as_sdt=2005&sciodt=0,5&hl=en","relatedUrl":"http://scholar.google.com/scholar?q=related:w31w6d1OceQJ:scholar.google.com/&scioq=&hl=en&as_sdt=2005&sciodt=0,5","urlVersionsList":"http://scholar.google.com/scholar?cluster=16461024828027076035&hl=en&as_sdt=2005&sciodt=0,5","publication":"Elsevier"},{"title":"Electrical energy storage systems: A comparative life cycle cost analysis","url":"https://www.sciencedirect.com/science/article/pii/S1364032114008284","authors":["B Zakeri","B Zakeri S Syri"],"year":2015,"numCitations":905,"pdf":"https://www.researchgate.net/profile/Behnam_Zakeri/publication/281277805_Electrical_energy_storage_systems_A_comparative_life_cycle_cost_analysis_2015/links/55deac0008ae79830bb58ede.pdf","citationUrl":"http://scholar.google.com/scholar?cites=11554153751654112746&as_sdt=2005&sciodt=0,5&hl=en","relatedUrl":"http://scholar.google.com/scholar?q=related:6h2X356ZWKAJ:scholar.google.com/&scioq=&hl=en&as_sdt=2005&sciodt=0,5","urlVersionsList":"http://scholar.google.com/scholar?cluster=11554153751654112746&hl=en&as_sdt=2005&sciodt=0,5","publication":"Elsevier"},{"title":"Review of energy storage system for wind power integration support","url":"https://www.sciencedirect.com/science/article/pii/S0306261914004668","authors":["H Zhao","H Zhao Q Wu","H Zhao Q Wu S Hu","H Zhao Q Wu S Hu H Xu","H Zhao Q Wu S Hu H Xu CN Rasmussen"],"year":2015,"numCitations":711,"citationUrl":"http://scholar.google.com/scholar?cites=9261566688773919643&as_sdt=2005&sciodt=0,5&hl=en","relatedUrl":"http://scholar.google.com/scholar?q=related:m9P1Y9Wxh4AJ:scholar.google.com/&scioq=&hl=en&as_sdt=2005&sciodt=0,5","urlVersionsList":"http://scholar.google.com/scholar?cluster=9261566688773919643&hl=en&as_sdt=2005&sciodt=0,5","publication":"Elsevier"},{"title":"Optimization in microgrids with hybrid energy systems–A review","url":"https://www.sciencedirect.com/science/article/pii/S1364032115000696","authors":["AH Fathima","AH Fathima K Palanisamy"],"year":2015,"numCitations":376,"citationUrl":"http://scholar.google.com/scholar?cites=10544462522284525101&as_sdt=2005&sciodt=0,5&hl=en","relatedUrl":"http://scholar.google.com/scholar?q=related:LUYwDMx0VZIJ:scholar.google.com/&scioq=&hl=en&as_sdt=2005&sciodt=0,5","urlVersionsList":"http://scholar.google.com/scholar?cluster=10544462522284525101&hl=en&as_sdt=2005&sciodt=0,5","publication":"Elsevier"},{"title":"Storage size determination for grid-connected photovoltaic systems","url":"https://ieeexplore.ieee.org/abstract/document/6216477/","authors":["Y Ru","Y Ru J Kleissl","Y Ru J Kleissl S Martinez"],"year":2012,"numCitations":337,"pdf":"https://arxiv.org/pdf/1109.4102","citationUrl":"http://scholar.google.com/scholar?cites=15687206455514399953&as_sdt=2005&sciodt=0,5&hl=en","relatedUrl":"http://scholar.google.com/scholar?q=related:0YQmKygntNkJ:scholar.google.com/&scioq=&hl=en&as_sdt=2005&sciodt=0,5","urlVersionsList":"http://scholar.google.com/scholar?cluster=15687206455514399953&hl=en&as_sdt=2005&sciodt=0,5","publication":"ieeexplore.ieee.org"},{"title":"Grid-scale energy storage applications in renewable energy integration: A survey","url":"https://www.sciencedirect.com/science/article/pii/S0196890414007018","authors":["A Castillo","A Castillo DF Gayme"],"year":2014,"numCitations":342,"citationUrl":"http://scholar.google.com/scholar?cites=4147924543253490986&as_sdt=2005&sciodt=0,5&hl=en","relatedUrl":"http://scholar.google.com/scholar?q=related:Kq2_O2VjkDkJ:scholar.google.com/&scioq=&hl=en&as_sdt=2005&sciodt=0,5","urlVersionsList":"http://scholar.google.com/scholar?cluster=4147924543253490986&hl=en&as_sdt=2005&sciodt=0,5","publication":"Elsevier"},{"title":"Optimal power flow in microgrids with energy storage","url":"https://ieeexplore.ieee.org/abstract/document/6469193/","authors":["Y Levron","Y Levron JM Guerrero","Y Levron JM Guerrero Y Beck"],"year":2013,"numCitations":329,"pdf":"https://madsg.com/wp-content/uploads/2014/02/06469193.pdf","citationUrl":"http://scholar.google.com/scholar?cites=9136886556912510017&as_sdt=2005&sciodt=0,5&hl=en","relatedUrl":"http://scholar.google.com/scholar?q=related:QeTPCeq9zH4J:scholar.google.com/&scioq=&hl=en&as_sdt=2005&sciodt=0,5","urlVersionsList":"http://scholar.google.com/scholar?cluster=9136886556912510017&hl=en&as_sdt=2005&sciodt=0,5","publication":"ieeexplore.ieee.org"},{"title":"Sizing energy storage to accommodate high penetration of variable energy resources","url":"https://ieeexplore.ieee.org/abstract/document/6095383/","authors":["YV Makarov","YV Makarov P Du","YV Makarov P Du MCW Kintner"],"year":2011,"numCitations":262,"pdf":"http://energyenvironment.pnnl.gov/ei/pdf/Sizing%20energy%20storage.pdf","citationUrl":"http://scholar.google.com/scholar?cites=4424735071278579522&as_sdt=2005&sciodt=0,5&hl=en","relatedUrl":"http://scholar.google.com/scholar?q=related:Qr_FpBrRZz0J:scholar.google.com/&scioq=&hl=en&as_sdt=2005&sciodt=0,5","urlVersionsList":"http://scholar.google.com/scholar?cluster=4424735071278579522&hl=en&as_sdt=2005&sciodt=0,5","publication":"ieeexplore.ieee.org"},{"title":"Whole-systems assessment of the value of energy storage in low-carbon electricity systems","url":"https://ieeexplore.ieee.org/abstract/document/6612755/","authors":["D Pudjianto","D Pudjianto M Aunedi","D Pudjianto M Aunedi P Djapic…"],"year":2013,"numCitations":213,"pdf":"https://spiral.imperial.ac.uk/bitstream/10044/1/63114/2/IEEE_WholeSystem_Storage.pdf","citationUrl":"http://scholar.google.com/scholar?cites=16803409812116263936&as_sdt=2005&sciodt=0,5&hl=en","relatedUrl":"http://scholar.google.com/scholar?q=related:ANSAIjK0MekJ:scholar.google.com/&scioq=&hl=en&as_sdt=2005&sciodt=0,5","urlVersionsList":"http://scholar.google.com/scholar?cluster=16803409812116263936&hl=en&as_sdt=2005&sciodt=0,5","publication":"ieeexplore.ieee.org"}]}