{"&cites=11753454870093374939&as_sdt=2005&sciodt=0,5&hl=en&scioq=infantry":[{"title":"Risk factors for training-related injuries among men and women in basic combat training","url":"https://www.safetylit.org/citations/index.php?fuseaction=citations.viewdetails&citationIds[]=citjournalarticle_180347_8","authors":["JJ Knapik","JJ Knapik MA Sharp","JJ Knapik MA Sharp M Canham"],"year":2001,"numCitations":578,"citationUrl":"http://scholar.google.com/scholar?cites=15593848738078714142&as_sdt=2005&sciodt=0,5&hl=en&scioq=infantry","relatedUrl":"http://scholar.google.com/scholar?q=related:Hulaus56aNgJ:scholar.google.com/&scioq=&hl=en&as_sdt=2005&sciodt=0,5","urlVersionsList":"http://scholar.google.com/scholar?cluster=15593848738078714142&hl=en&as_sdt=2005&sciodt=0,5&scioq=infantry","publication":"safetylit.org","p":1,"exp":1596884751956},{"title":"Cigarette smoking and exercise-related injuries among young men and women","url":"https://www.sciencedirect.com/science/article/pii/S074937979900166X","authors":["M Altarac","M Altarac JW Gardner","M Altarac JW Gardner RM Popovich","M Altarac JW Gardner RM Popovich R Potter…"],"year":2000,"numCitations":174,"pdf":"https://www.ajpmonline.org/article/S0749-3797%2899%2900166-X/fulltext","citationUrl":"http://scholar.google.com/scholar?cites=9980385215408261861&as_sdt=2005&sciodt=0,5&hl=en&scioq=infantry","relatedUrl":"http://scholar.google.com/scholar?q=related:5Ur4nXlzgYoJ:scholar.google.com/&scioq=&hl=en&as_sdt=2005&sciodt=0,5","urlVersionsList":"http://scholar.google.com/scholar?cluster=9980385215408261861&hl=en&as_sdt=2005&sciodt=0,5&scioq=infantry","publication":"Elsevier"},{"title":"Incidence of injury and physical performance adaptations during military training","url":"https://journals.lww.com/cjsportsmed/Fulltext/2003/05000/Incidence_of_Injury_and_Physical_Performance.6.aspx","authors":["L Rosendal","L Rosendal H Langberg","L Rosendal H Langberg A Skov"],"year":2003,"numCitations":144,"pdf":"http://citeseerx.ist.psu.edu/viewdoc/download?doi=10.1.1.533.7270&rep=rep1&type=pdf","citationUrl":"http://scholar.google.com/scholar?cites=14837536509254539234&as_sdt=2005&sciodt=0,5&hl=en&scioq=infantry","relatedUrl":"http://scholar.google.com/scholar?q=related:4pcBsNeE6c0J:scholar.google.com/&scioq=&hl=en&as_sdt=2005&sciodt=0,5","urlVersionsList":"http://scholar.google.com/scholar?cluster=14837536509254539234&hl=en&as_sdt=2005&sciodt=0,5&scioq=infantry","publication":"journals.lww.com"},{"title":"Injury reduction effectiveness of selecting running shoes based on plantar shape","url":"https://journals.lww.com/nsca-jscr/fulltext/2009/05000/Injury_Reduction_Effectiveness_of_Selecting.1.aspx","authors":["JJ Knapik","JJ Knapik DI Swedler","JJ Knapik DI Swedler TL Grier…"],"year":2009,"numCitations":129,"pdf":"https://www.practice-field.com/uploads/1/3/1/6/131695905/2009_army_injury_reduction.pdf","citationUrl":"http://scholar.google.com/scholar?cites=704917516330497148&as_sdt=2005&sciodt=0,5&hl=en&scioq=infantry","relatedUrl":"http://scholar.google.com/scholar?q=related:fHTUDL9eyAkJ:scholar.google.com/&scioq=&hl=en&as_sdt=2005&sciodt=0,5","urlVersionsList":"http://scholar.google.com/scholar?cluster=704917516330497148&hl=en&as_sdt=2005&sciodt=0,5&scioq=infantry","publication":"journals.lww.com"},{"title":"Summary of the epidemiological evidence relating snus to health","url":"https://www.sciencedirect.com/science/article/pii/S0273230010002229","authors":["PN Lee"],"year":2011,"numCitations":127,"citationUrl":"http://scholar.google.com/scholar?cites=13222040059671197074&as_sdt=2005&sciodt=0,5&hl=en&scioq=infantry","relatedUrl":"http://scholar.google.com/scholar?q=related:krWvgmEffrcJ:scholar.google.com/&scioq=&hl=en&as_sdt=2005&sciodt=0,5","urlVersionsList":"http://scholar.google.com/scholar?cluster=13222040059671197074&hl=en&as_sdt=2005&sciodt=0,5&scioq=infantry","publication":"Elsevier"},{"title":"Increasing the physical fitness of low-fit recruits before basic combat training: an evaluation of fitness, injuries, and training outcomes","url":"https://academic.oup.com/milmed/article-abstract/171/1/45/4577767","authors":["JJ Knapik","JJ Knapik S Darakjy","JJ Knapik S Darakjy KG Hauret","JJ Knapik S Darakjy KG Hauret S Canada…"],"year":2006,"numCitations":117,"pdf":"https://academic.oup.com/milmed/article-pdf/171/1/45/21978654/milmed.171.1.45.pdf","citationUrl":"http://scholar.google.com/scholar?cites=6317635780893981409&as_sdt=2005&sciodt=0,5&hl=en&scioq=infantry","relatedUrl":"http://scholar.google.com/scholar?q=related:4bp7PEXArFcJ:scholar.google.com/&scioq=&hl=en&as_sdt=2005&sciodt=0,5","urlVersionsList":"http://scholar.google.com/scholar?cluster=6317635780893981409&hl=en&as_sdt=2005&sciodt=0,5&scioq=infantry","publication":"academic.oup.com"},{"title":"Risk factors for training injuries among British Army recruits","url":"https://academic.oup.com/milmed/article-abstract/173/3/278/4557711","authors":["SD Blacker","SD Blacker DM Wilkinson","SD Blacker DM Wilkinson JLJ Bilzon…"],"year":2008,"numCitations":104,"pdf":"https://academic.oup.com/milmed/article/173/3/278/4557711","citationUrl":"http://scholar.google.com/scholar?cites=1984111898389349945&as_sdt=2005&sciodt=0,5&hl=en&scioq=infantry","relatedUrl":"http://scholar.google.com/scholar?q=related:OYYfYkL7iBsJ:scholar.google.com/&scioq=&hl=en&as_sdt=2005&sciodt=0,5","urlVersionsList":"http://scholar.google.com/scholar?cluster=1984111898389349945&hl=en&as_sdt=2005&sciodt=0,5&scioq=infantry","publication":"academic.oup.com"},{"title":"Primary care consultation, hospital admission, sick leave and disability pension owing to neck and low back pain: a 12-year prospective cohort study in a rural …","url":"https://link.springer.com/article/10.1186/1471-2474-7-66","authors":["SAC Holmberg","SAC Holmberg AG Thelin"],"year":2006,"numCitations":101,"pdf":"https://link.springer.com/article/10.1186/1471-2474-7-66","citationUrl":"http://scholar.google.com/scholar?cites=8813882686554908658&as_sdt=2005&sciodt=0,5&hl=en&scioq=infantry","relatedUrl":"http://scholar.google.com/scholar?q=related:8icSAJszUXoJ:scholar.google.com/&scioq=&hl=en&as_sdt=2005&sciodt=0,5","urlVersionsList":"http://scholar.google.com/scholar?cluster=8813882686554908658&hl=en&as_sdt=2005&sciodt=0,5&scioq=infantry","publication":"Springer"},{"title":"Effect on injuries of assigning shoes based on foot shape in air force basic training","url":"https://www.sciencedirect.com/science/article/pii/S0749379709006643","authors":["JJ Knapik","JJ Knapik LC Brosch","JJ Knapik LC Brosch M Venuto","JJ Knapik LC Brosch M Venuto DI Swedler…"],"year":2010,"numCitations":99,"pdf":"http://phc.amedd.army.mil/PHC%20Resource%20Library/Effect%20on%20Injuries%20of%20Assigning%20Shoes%20Based%20on%20Foot%20Shape%20in%20Air%20Force%20Basic%20Military%20Training.pdf","citationUrl":"http://scholar.google.com/scholar?cites=14540887082467642380&as_sdt=2005&sciodt=0,5&hl=en&scioq=infantry","relatedUrl":"http://scholar.google.com/scholar?q=related:DMyMtcKby8kJ:scholar.google.com/&scioq=&hl=en&as_sdt=2005&sciodt=0,5","urlVersionsList":"http://scholar.google.com/scholar?cluster=14540887082467642380&hl=en&as_sdt=2005&sciodt=0,5&scioq=infantry","publication":"Elsevier"},{"title":"Extreme conditioning programs and injury risk in a US Army Brigade Combat Team.","url":"https://www.researchgate.net/profile/Erin_Gaffney-Stomberg/publication/258065716_Assessment_of_dietary_intake_using_the_healthy_eating_index_during_military_training/links/56019a8e08aed9851827c85b/Assessment-of-dietary-intake-using-the-healthy-eating-index-during-military-training.pdf#page=38","authors":["T Grier","T Grier M Canham"],"year":2013,"numCitations":92,"pdf":"https://www.researchgate.net/profile/Erin_Gaffney-Stomberg/publication/258065716_Assessment_of_dietary_intake_using_the_healthy_eating_index_during_military_training/links/56019a8e08aed9851827c85b/Assessment-of-dietary-intake-using-the-healthy-eating-index-during-military-training.pdf#page=38","citationUrl":"http://scholar.google.com/scholar?cites=10230582347491626233&as_sdt=2005&sciodt=0,5&hl=en&scioq=infantry","relatedUrl":"http://scholar.google.com/scholar?q=related:-cye63BU-o0J:scholar.google.com/&scioq=&hl=en&as_sdt=2005&sciodt=0,5","urlVersionsList":"http://scholar.google.com/scholar?cluster=10230582347491626233&hl=en&as_sdt=2005&sciodt=0,5&scioq=infantry","publication":"researchgate.net"}]}