{"related:qjBP0NXOXWwJ:scholar.google.com/&scioq=&hl=en&as_sdt=2005&sciodt=0,5":[{"title":"Alternatives to P value: confidence interval and effect size","url":"https://www.ncbi.nlm.nih.gov/pmc/articles/PMC5133225/","authors":["DK Lee"],"year":2016,"numCitations":110,"pdf":"https://www.ncbi.nlm.nih.gov/pmc/articles/PMC5133225/","citationUrl":"http://scholar.google.com/scholar?cites=7808624746648514730&as_sdt=2005&sciodt=0,5&hl=en","relatedUrl":"http://scholar.google.com/scholar?q=related:qjBP0NXOXWwJ:scholar.google.com/&scioq=&hl=en&as_sdt=0,5","urlVersionsList":"http://scholar.google.com/scholar?cluster=7808624746648514730&hl=en&as_sdt=0,5","publication":"ncbi.nlm.nih.gov","p":1,"exp":1596879339450},{"title":"Why the P-value culture is bad and confidence intervals a better alternative","url":"https://www.sciencedirect.com/science/article/pii/S1063458412007789","authors":["J Ranstam"],"year":2012,"numCitations":64,"pdf":"https://www.sciencedirect.com/science/article/pii/S1063458412007789","citationUrl":"http://scholar.google.com/scholar?cites=16150820140928313484&as_sdt=2005&sciodt=0,5&hl=en","relatedUrl":"http://scholar.google.com/scholar?q=related:jKhB81g9I-AJ:scholar.google.com/&scioq=&hl=en&as_sdt=0,5","urlVersionsList":"http://scholar.google.com/scholar?cluster=16150820140928313484&hl=en&as_sdt=0,5","publication":"Elsevier"},{"title":"P values and effect size","url":"https://journals.sagepub.com/doi/pdf/10.1177/0145482X1611000111","authors":["RW Emerson"],"year":2016,"numCitations":5,"citationUrl":"http://scholar.google.com/scholar?cites=14185723095358605111&as_sdt=2005&sciodt=0,5&hl=en","relatedUrl":"http://scholar.google.com/scholar?q=related:N4fn_P7P3cQJ:scholar.google.com/&scioq=&hl=en&as_sdt=0,5","urlVersionsList":"http://scholar.google.com/scholar?cluster=14185723095358605111&hl=en&as_sdt=0,5","publication":"journals.sagepub.com"},{"title":"Testing differences in proportions","url":"https://www.sciencedirect.com/science/article/pii/S1036731411000488","authors":["MJ Fisher","MJ Fisher AP Marshall","MJ Fisher AP Marshall M Mitchell"],"year":2011,"numCitations":25,"pdf":"https://research-repository.griffith.edu.au/bitstream/handle/10072/43755/77193_1.pdf?sequence=1","citationUrl":"http://scholar.google.com/scholar?cites=4681072252906684814&as_sdt=2005&sciodt=0,5&hl=en","relatedUrl":"http://scholar.google.com/scholar?q=related:jsFwommC9kAJ:scholar.google.com/&scioq=&hl=en&as_sdt=0,5","urlVersionsList":"http://scholar.google.com/scholar?cluster=4681072252906684814&hl=en&as_sdt=0,5","publication":"Elsevier"},{"title":"The importance of effect sizes in the interpretation of research: Primer on research: Part 3","url":"https://leader.pubs.asha.org/doi/full/10.1044/leader.FTR4.11102006.14","authors":["CM Schuele","CM Schuele LM Justice"],"year":2006,"numCitations":46,"pdf":"https://leader.pubs.asha.org/doi/full/10.1044/leader.FTR4.11102006.14","citationUrl":"http://scholar.google.com/scholar?cites=1331915539816018971&as_sdt=2005&sciodt=0,5&hl=en","relatedUrl":"http://scholar.google.com/scholar?q=related:G3SObSDqexIJ:scholar.google.com/&scioq=&hl=en&as_sdt=0,5","publication":"ASHA"},{"title":"Measuring magnitude of treatment effects in agricultural experiments","url":"https://www.academia.edu/download/33286127/APUAN__2014._Measuring_magnitude_of_treatment_effects.pdf","authors":["DA Apuan"],"year":2014,"numCitations":0,"pdf":"https://www.academia.edu/download/33286127/APUAN__2014._Measuring_magnitude_of_treatment_effects.pdf","relatedUrl":"http://scholar.google.com/scholar?q=related:jY0gaeEdhM8J:scholar.google.com/&scioq=&hl=en&as_sdt=0,5","urlVersionsList":"http://scholar.google.com/scholar?cluster=14953109516745477517&hl=en&as_sdt=0,5","publication":"academia.edu"},{"title":"Reporting of effect size and confidence intervals: Review and methods of calculation","url":"http://psyct.psychopen.eu/article/view/92","authors":["MR Vasilev"],"year":2014,"numCitations":3,"pdf":"https://psyct.psychopen.eu/article/download/92/92","citationUrl":"http://scholar.google.com/scholar?cites=6115830622038192688&as_sdt=2005&sciodt=0,5&hl=en","relatedUrl":"http://scholar.google.com/scholar?q=related:MPIKNYzL31QJ:scholar.google.com/&scioq=&hl=en&as_sdt=0,5","urlVersionsList":"http://scholar.google.com/scholar?cluster=6115830622038192688&hl=en&as_sdt=0,5","publication":"psyct.psychopen.eu"},{"title":"Докладване на големина на ефекта и доверителни интервали: Преглед и начини за изчисляване","url":"https://psycharchives.org/handle/20.500.12034/1579","authors":["MR Vasilev"],"year":2014,"numCitations":0,"pdf":"https://psycharchives.org/bitstream/20.500.12034/1579/1/psyct.v7i1.92.pdf","relatedUrl":"http://scholar.google.com/scholar?q=related:O8gJeK99JXEJ:scholar.google.com/&scioq=&hl=en&as_sdt=0,5","urlVersionsList":"http://scholar.google.com/scholar?cluster=8153060893010806843&hl=en&as_sdt=0,5","publication":"psycharchives.org"},{"title":"Facial reanimation by muscle-nerve neurotization after facial nerve sacrifice. Case report","url":"https://www.sciencedirect.com/science/article/pii/S0294126015001326","authors":["A Taupin","A Taupin D Labbé","A Taupin D Labbé E Babin","A Taupin D Labbé E Babin G Fromager"],"year":2016,"numCitations":3,"citationUrl":"http://scholar.google.com/scholar?cites=15815617777003417165&as_sdt=2005&sciodt=0,5&hl=en","relatedUrl":"http://scholar.google.com/scholar?q=related:TU6kzZJcfNsJ:scholar.google.com/&scioq=&hl=en&as_sdt=0,5","urlVersionsList":"http://scholar.google.com/scholar?cluster=15815617777003417165&hl=en&as_sdt=0,5","publication":"Elsevier"}]}