{"related:ihU0eC_I6mIJ:scholar.google.com/&scioq=meta-philosophy&hl=en&as_sdt=0,5":[{"title":"Philosophy without intuitions","url":"https://books.google.com/books?hl=en&lr=&id=u6UfclVFOtwC&oi=fnd&pg=PP1&dq=related:ihU0eC_I6mIJ:scholar.google.com/&ots=Uvl65Yw9Cj&sig=fbQlciD_BkhvocInvuktGytOZEM","authors":["H Cappelen"],"year":2012,"numCitations":530,"pdf":"http://www.klemens.sav.sk/fiusav/doc/filozofia/2013/7/625-628.pdf","citationUrl":"http://scholar.google.com/scholar?cites=7127729466472928650&as_sdt=2005&sciodt=0,5&hl=en&scioq=meta-philosophy","relatedUrl":"http://scholar.google.com/scholar?q=related:ihU0eC_I6mIJ:scholar.google.com/&scioq=meta-philosophy&hl=en&as_sdt=0,5","urlVersionsList":"http://scholar.google.com/scholar?cluster=7127729466472928650&hl=en&as_sdt=0,5&scioq=meta-philosophy","publication":"books.google.com","p":1,"exp":1596876805744},{"title":"Intuitions, counter-examples, and experimental philosophy","url":"https://link.springer.com/content/pdf/10.1007/s13164-010-0033-0.pdf","authors":["M Deutsch"],"year":2010,"numCitations":122,"pdf":"https://www.finophd.eu/wp-content/uploads/2018/01/018-Deutsch_intuitions-counter-examples.pdf","citationUrl":"http://scholar.google.com/scholar?cites=3184630586364568855&as_sdt=2005&sciodt=0,5&hl=en&scioq=meta-philosophy","relatedUrl":"http://scholar.google.com/scholar?q=related:F6UaOaUUMiwJ:scholar.google.com/&scioq=meta-philosophy&hl=en&as_sdt=0,5","urlVersionsList":"http://scholar.google.com/scholar?cluster=3184630586364568855&hl=en&as_sdt=0,5&scioq=meta-philosophy","publication":"Springer"},{"title":"The epistemology of thought experiments: First person versus third person approaches","url":"https://www.pdcnet.org/msp/content/msp_2007_0031_0128_0159","authors":["K Ludwig"],"year":2007,"numCitations":318,"pdf":"https://philpapers.org/archive/LUDTEO.pdf","citationUrl":"http://scholar.google.com/scholar?cites=6796527792402181749&as_sdt=2005&sciodt=0,5&hl=en&scioq=meta-philosophy","relatedUrl":"http://scholar.google.com/scholar?q=related:da4zhAQeUl4J:scholar.google.com/&scioq=meta-philosophy&hl=en&as_sdt=0,5","urlVersionsList":"http://scholar.google.com/scholar?cluster=6796527792402181749&hl=en&as_sdt=0,5&scioq=meta-philosophy","publication":"pdcnet.org"},{"title":"Philosophical intuitions: Their target, their source, and their epistemic status","url":"https://brill.com/view/journals/gps/74/1/article-p1_2.xml","authors":["AI Goldman"],"year":2007,"numCitations":282,"pdf":"http://fas-philosophy.rutgers.edu/goldman/Philosophical%20Intuitions.pdf","citationUrl":"http://scholar.google.com/scholar?cites=1140284288371514821&as_sdt=2005&sciodt=0,5&hl=en&scioq=meta-philosophy","relatedUrl":"http://scholar.google.com/scholar?q=related:xd1Xz4Qa0w8J:scholar.google.com/&scioq=meta-philosophy&hl=en&as_sdt=0,5","urlVersionsList":"http://scholar.google.com/scholar?cluster=1140284288371514821&hl=en&as_sdt=0,5&scioq=meta-philosophy","publication":"brill.com"},{"title":"The instability of philosophical intuitions: Running hot and cold on truetemp","url":"https://onlinelibrary.wiley.com/doi/abs/10.1111/j.1933-1592.2007.00118.x","authors":["S Swain","S Swain J Alexander…"],"year":2008,"numCitations":390,"citationUrl":"http://scholar.google.com/scholar?cites=17434878843902027093&as_sdt=2005&sciodt=0,5&hl=en&scioq=meta-philosophy","relatedUrl":"http://scholar.google.com/scholar?q=related:VeXAQO8h9fEJ:scholar.google.com/&scioq=meta-philosophy&hl=en&as_sdt=0,5","urlVersionsList":"http://scholar.google.com/scholar?cluster=17434878843902027093&hl=en&as_sdt=0,5&scioq=meta-philosophy","publication":"Wiley Online Library"},{"title":"How to challenge intuitions empirically without risking skepticism","url":"https://www.pdcnet.org/msp/content/msp_2007_0031_0318_0343","authors":["JM Weinberg"],"year":2007,"numCitations":267,"citationUrl":"http://scholar.google.com/scholar?cites=8213549730538021233&as_sdt=2005&sciodt=0,5&hl=en&scioq=meta-philosophy","relatedUrl":"http://scholar.google.com/scholar?q=related:cWG5cfZj_HEJ:scholar.google.com/&scioq=meta-philosophy&hl=en&as_sdt=0,5","urlVersionsList":"http://scholar.google.com/scholar?cluster=8213549730538021233&hl=en&as_sdt=0,5&scioq=meta-philosophy","publication":"pdcnet.org"},{"title":"Normativity and epistemic intuitions","url":"https://www.pdcnet.org/philtopics/content/philtopics_2001_0029_0001_0429_0460","authors":["JM Weinberg","JM Weinberg S Nichols","JM Weinberg S Nichols S Stich"],"year":2001,"numCitations":922,"pdf":"http://citeseerx.ist.psu.edu/viewdoc/download?doi=10.1.1.174.4748&rep=rep1&type=pdf","citationUrl":"http://scholar.google.com/scholar?cites=9905156931458996455&as_sdt=2005&sciodt=0,5&hl=en&scioq=meta-philosophy","relatedUrl":"http://scholar.google.com/scholar?q=related:55gc2L8vdokJ:scholar.google.com/&scioq=meta-philosophy&hl=en&as_sdt=0,5","urlVersionsList":"http://scholar.google.com/scholar?cluster=9905156931458996455&hl=en&as_sdt=0,5&scioq=meta-philosophy","publication":"pdcnet.org"},{"title":"Semantics, cross-cultural style","url":"https://www.sciencedirect.com/science/article/pii/S0010027703002087","authors":["E Machery","E Machery R Mallon","E Machery R Mallon S Nichols","E Machery R Mallon S Nichols SP Stich"],"year":2004,"numCitations":618,"pdf":"https://jeannicod.ccsd.cnrs.fr/ijn_00000399/document","citationUrl":"http://scholar.google.com/scholar?cites=17584332614223964281&as_sdt=2005&sciodt=0,5&hl=en&scioq=meta-philosophy","relatedUrl":"http://scholar.google.com/scholar?q=related:eagiy1gZCPQJ:scholar.google.com/&scioq=meta-philosophy&hl=en&as_sdt=0,5","urlVersionsList":"http://scholar.google.com/scholar?cluster=17584332614223964281&hl=en&as_sdt=0,5&scioq=meta-philosophy","publication":"Elsevier"},{"title":"Philosophical expertise and the burden of proof","url":"https://onlinelibrary.wiley.com/doi/abs/10.1111/j.1467-9973.2011.01685.x","authors":["T Williamson"],"year":2011,"numCitations":190,"citationUrl":"http://scholar.google.com/scholar?cites=5123477228592758012&as_sdt=2005&sciodt=0,5&hl=en&scioq=meta-philosophy","relatedUrl":"http://scholar.google.com/scholar?q=related:_PwS4WQ_GkcJ:scholar.google.com/&scioq=meta-philosophy&hl=en&as_sdt=0,5","urlVersionsList":"http://scholar.google.com/scholar?cluster=5123477228592758012&hl=en&as_sdt=0,5&scioq=meta-philosophy","publication":"Wiley Online Library"},{"title":"Are philosophers expert intuiters?","url":"https://www.tandfonline.com/doi/abs/10.1080/09515089.2010.490944","authors":["JM Weinberg","JM Weinberg C Gonnerman","JM Weinberg C Gonnerman C Buckner…"],"year":2010,"numCitations":226,"citationUrl":"http://scholar.google.com/scholar?cites=12724317481707000633&as_sdt=2005&sciodt=0,5&hl=en&scioq=meta-philosophy","relatedUrl":"http://scholar.google.com/scholar?q=related:OVNwUlXblbAJ:scholar.google.com/&scioq=meta-philosophy&hl=en&as_sdt=0,5","urlVersionsList":"http://scholar.google.com/scholar?cluster=12724317481707000633&hl=en&as_sdt=0,5&scioq=meta-philosophy","publication":"Taylor & Francis"}]}